CircuitSeeker/__init__.py
CircuitSeeker/fileio.py
CircuitSeeker/function.py
CircuitSeeker/quality.py
CircuitSeeker-1.0.1.dist-info/LICENSE.txt
CircuitSeeker-1.0.1.dist-info/METADATA
CircuitSeeker-1.0.1.dist-info/WHEEL
CircuitSeeker-1.0.1.dist-info/top_level.txt
CircuitSeeker-1.0.1.dist-info/RECORD
