Metadata-Version: 2.2
Name: CircuitSeeker
Version: 1.0.1
Summary: Tools for finding neural circuits
Home-page: https://github.com/GFleishman/CircuitSeeker
Author: Greg M. Fleishman
Author-email: greg.nli10me@gmail.com
License: MIT
License-File: LICENSE.txt
Requires-Dist: numpy
Requires-Dist: scipy
Requires-Dist: h5py
Requires-Dist: bokeh
Requires-Dist: dask
Requires-Dist: dask[array]
Requires-Dist: dask[bag]
Requires-Dist: dask[delayed]
Requires-Dist: dask[distributed]
Requires-Dist: dask-jobqueue
Requires-Dist: SimpleITK
Requires-Dist: zarr
Requires-Dist: numcodecs
Requires-Dist: ClusterWrap
Dynamic: author
Dynamic: author-email
Dynamic: home-page
Dynamic: license
Dynamic: requires-dist
Dynamic: summary
